{
    "search-placeholder": "Искать...",
    "sort-by": "сортировать по",
    "sort-by-title": "Названию",
    "sort-by-artist": "Исполнителю",
    "sort-by-length": "Длительности",
    "sort-by-date-added": "Дате загрузки",
    "sort-by-difficulty": "Сложности",
    "group-by": "групировать по",
    "group-by-default": "Карте",
    "group-by-nothing": "Ничего ...",
    "footer-mods": "Моды",
    "footer-random": "Случайно",
    "footer-rewind": "Обратно",
    "footer-options": "Настройки",
    "footer-practice": "Практика",
    "leaderboard-title": "Рекорды",
    "leaderboard-local": "Локальные",
    "leaderboard-global": "Мировые",
    "leaderboard-country": "Страны",
    "leaderboard-friends": "Друзей",
    "leaderboard-club": "Клуба",
    "leaderboard-out-of-date": "Есть новая версия карты!",
    "leaderboard-no-scores": "Пока ничего!",
    "leaderboard-scores-unavailable": "Не доступно для карты!",
    "leaderboard-not-uploaded": "Эта карта не опубликована!",
    "options-settings": "Настройки игры",
    "options-for-all": "Для всех сложностей",
    "options-for-current": "Для этой сложности",
    "options-delete": "Удалить мапсет",
    "options-wipe-scores": "Стереть локальные рекорды",
    "wipe-scores-title": "Вы точно хотите стереть ВСЕ локальные рекорды для этой сложности?",
    "no-maps-title": "Карты не найдены!",
    "no-maps-description": "Попробуйте изменить фильтры поиска."
}
