{
  "general": "General",
  "back": "Volver",
  "play": "Jugar",
  "edit": "Editar",
  "select": "Seleccionar",
  "delete": "Borrar",
  "export": "Exportar",
  "refresh": "Recargar",
  "view-online": "Ver en Linea",
  "panel-generic-confirm": "Confirmar",
  "panel-generic-cancel": "Cancelar",
  "panel-confirm-exit": "¿Salir?",
  "map-bpm": "BPM",
  "map-length": "Duracion",
  "map-rating": "Dificultad",
  "map-nps": "NPS",
  "map-hits": "Notas",
  "map-lns": "LNs",
  "map-lnp": "LN%",
  "map-acc": "Precision",
  "map-hp": "Vida",
  "status-online": "En Linea",
  "status-offline": "Desconectado",
  "status-playing": "Jugando",
  "status-watching-replay": "Mirando Replay",
  "status-editing": "Editando",
  "status-multiplayer": "Jugando Multijugador",
  "can-not-be-undone": "Nada para deshacer",
  "login-to-use": "Inicia sesion para usar esta funcion"
}